gitvault/__init__.py
gitvault/cloud_sync.py
gitvault/custom_exceptions.py
gitvault/decorators.py
gitvault/decrypt_data.py
gitvault/encrypt_data.py
gitvault/git_fetch.py
gitvault-0.1.0.dist-info/METADATA
gitvault-0.1.0.dist-info/WHEEL
gitvault-0.1.0.dist-info/top_level.txt
gitvault-0.1.0.dist-info/RECORD
