Metadata-Version: 2.1
Name: gitvault
Version: 0.1.0
Summary: A package for secure data encryption and decryption with Git integration
Home-page: https://github.com/ayush1920/GitValult
Author: Ayush Kumar
Author-email: ayushkumar1221@gmail.com
Classifier: Programming Language :: Python :: 3
Classifier: License :: OSI Approved :: MIT License
Classifier: Operating System :: OS Independent
Requires-Python: >=3.7
Requires-Dist: cryptography
Requires-Dist: GitPython
Requires-Dist: pytest
Requires-Dist: python-dotenv
Requires-Dist: requests
Requires-Dist: setuptools
Requires-Dist: urllib3
